README.md
setup.py
clay/__init__.py
clay/app.py
clay/clipboard.py
clay/colours.yaml
clay/config.yaml
clay/eventhook.py
clay/gp.py
clay/hotkeys.py
clay/log.py
clay/meta.py
clay/notifications.py
clay/osd.py
clay/playbar.py
clay/player.py
clay/settings.py
clay/songlist.py
clay/vlc.py
clay/pages/__init__.py
clay/pages/debug.py
clay/pages/mylibrary.py
clay/pages/myplaylists.py
clay/pages/mystations.py
clay/pages/page.py
clay/pages/playerqueue.py
clay/pages/search.py
clay/pages/settings.py
clay_player.egg-info/PKG-INFO
clay_player.egg-info/SOURCES.txt
clay_player.egg-info/dependency_links.txt
clay_player.egg-info/entry_points.txt
clay_player.egg-info/requires.txt
clay_player.egg-info/top_level.txt
images/clay-banner.png
images/clay-screenshot.png