Metadata-Version: 1.0
Name: clay-player
Version: 1.1.0
Summary: Command Line Player for Google Play Music
Home-page: https://github.com/and3rson/clay
Author: Andrew Dunai
Author-email: a@dun.ai
License: UNKNOWN
Platform: UNKNOWN
